kryten_cli.py
kryten_cli-2.5.1.dist-info/entry_points.txt
kryten_cli-2.5.1.dist-info/licenses/LICENSE
kryten_cli-2.5.1.dist-info/METADATA
kryten_cli-2.5.1.dist-info/WHEEL
kryten_cli-2.5.1.dist-info/RECORD
