Metadata-Version: 2.4
Name: kryten-cli
Version: 2.5.1
Summary: Command-line client for CyTube via kryten-py library
License: MIT
License-File: LICENSE
Keywords: cytube,nats,cli,command-line,microservices,bot
Author: Kryten Robot Team
Author-email: kryten@example.com
Requires-Python: >=3.10
Classifier: Development Status :: 4 - Beta
Classifier: Intended Audience :: Developers
Classifier: License :: OSI Approved :: MIT License
Classifier: Programming Language :: Python :: 3
Classifier: Programming Language :: Python :: 3.10
Classifier: Programming Language :: Python :: 3.11
Classifier: Programming Language :: Python :: 3.12
Classifier: Programming Language :: Python :: 3.13
Classifier: Programming Language :: Python :: 3.14
Classifier: Topic :: Communications :: Chat
Classifier: Topic :: Utilities
Requires-Dist: kryten-py (>=0.9.8)
Project-URL: Documentation, https://github.com/grobertson/kryten-cli/blob/main/README.md
Project-URL: Homepage, https://github.com/grobertson/kryten-cli
Project-URL: Repository, https://github.com/grobertson/kryten-cli
